<mxfile host='Electron' modified='24/06/2021 15:05:31' agent='BHoM' type='device'>
    <diagram id='2bffd2a8-4bdd-4af0-9f4e-e21291a84c88'>
        <mxGraphModel dx='-1266' dy='2416' grid='1' gridSize='10' guides='1' tooltips='1' connect='1' arrows='1' fold='1' page='1' pageScale='1' pageWidth='1169' pageHeight='827' math='0' shadow='0'>
            <root>
                <mxCell id="b9f28b03-3f2a-45a1-b849-d2f081614027" />
                <mxCell id="80db5337-4938-4a5a-b9cc-148fda11be39" parent="b9f28b03-3f2a-45a1-b849-d2f081614027" />
                <mxCell id="b69612b4-543a-46ba-b709-f70349fadb83" value="&lt;&lt;enumeration&gt;&gt;&#xD;&#xA;ConcreteDesignSpecification" style="swimlane;fontStyle=0;childLayout=stackLayout;horizontal=1;startSize=42;fillColor=none;horizontalStack=0;resizeParent=1;resizeParentMax=0;resizeLast=0;collapsible=1;marginBottom=0;fontSize=12;align=center;" vertex="1" collapsed="1" parent="80db5337-4938-4a5a-b9cc-148fda11be39">
                    <mxGeometry x="0" y="0" width="200" height="42" as="geometry">
                        <mxRectangle x='0' y='0' width='230' height='192' as='alternateBounds' />
                    </mxGeometry>
                </mxCell>
                <mxCell id="d6a97ec1-99ce-4f6c-8731-b1b2f3e0db0c" value="Eurocode1992" style="text;strokeColor=none;fillColor=none;align=left;verticalAlign=top;spacingLeft=4;spacingRight=4;overflow=hidden;rotatable=0;points=[[0,0.5],[1,0.5]];portConstraint=eastwest;fontColor=#000000" vertex="1" parent="b69612b4-543a-46ba-b709-f70349fadb83">
                    <mxGeometry y='26' width='150' height='26' as='geometry' />
                </mxCell>
                <mxCell id="f712569e-650e-4561-8cd5-69237b7856bf" value="ACI" style="text;strokeColor=none;fillColor=none;align=left;verticalAlign=top;spacingLeft=4;spacingRight=4;overflow=hidden;rotatable=0;points=[[0,0.5],[1,0.5]];portConstraint=eastwest;fontColor=#000000" vertex="1" parent="b69612b4-543a-46ba-b709-f70349fadb83">
                    <mxGeometry y='26' width='150' height='26' as='geometry' />
                </mxCell>
            </root>
        </mxGraphModel dx='-1266' dy='2416' grid='1' gridSize='10' guides='1' tooltips='1' connect='1' arrows='1' fold='1' page='1' pageScale='1' pageWidth='1169' pageHeight='827' math='0' shadow='0'>
    </diagram id='2bffd2a8-4bdd-4af0-9f4e-e21291a84c88'>
</mxfile host='Electron' modified='24/06/2021 15:05:31' agent='BHoM' type='device'>