<mxfile host='Electron' modified='24/06/2021 15:05:18' agent='BHoM' type='device'>
    <diagram id='af4a872b-a1f0-4bc1-b211-2ba1853a3685'>
        <mxGraphModel dx='-1266' dy='2416' grid='1' gridSize='10' guides='1' tooltips='1' connect='1' arrows='1' fold='1' page='1' pageScale='1' pageWidth='1169' pageHeight='827' math='0' shadow='0'>
            <root>
                <mxCell id="5a95d095-a0af-4045-9791-a020464c6c54" />
                <mxCell id="04fa581e-0faf-418e-baf5-0bd5a154019e" parent="5a95d095-a0af-4045-9791-a020464c6c54" />
                <mxCell id="a33fc998-6909-4699-b236-76cd1d775efd" value="&lt;&lt;enumeration&gt;&gt;&#xD;&#xA;SurfaceConvectionAlgorithmOutsideMethod" style="swimlane;fontStyle=0;childLayout=stackLayout;horizontal=1;startSize=42;fillColor=none;horizontalStack=0;resizeParent=1;resizeParentMax=0;resizeLast=0;collapsible=1;marginBottom=0;fontSize=12;align=center;" vertex="1" collapsed="1" parent="04fa581e-0faf-418e-baf5-0bd5a154019e">
                    <mxGeometry x="0" y="0" width="200" height="42" as="geometry">
                        <mxRectangle x='0' y='0' width='230' height='192' as='alternateBounds' />
                    </mxGeometry>
                </mxCell>
                <mxCell id="a228c61c-0f2d-48c1-8cb5-38a759493310" value="Undefined" style="text;strokeColor=none;fillColor=none;align=left;verticalAlign=top;spacingLeft=4;spacingRight=4;overflow=hidden;rotatable=0;points=[[0,0.5],[1,0.5]];portConstraint=eastwest;fontColor=#000000" vertex="1" parent="a33fc998-6909-4699-b236-76cd1d775efd">
                    <mxGeometry y='26' width='150' height='26' as='geometry' />
                </mxCell>
                <mxCell id="c2d67267-2339-4e0c-9d8c-c1049b4e07f1" value="SimpleCombined" style="text;strokeColor=none;fillColor=none;align=left;verticalAlign=top;spacingLeft=4;spacingRight=4;overflow=hidden;rotatable=0;points=[[0,0.5],[1,0.5]];portConstraint=eastwest;fontColor=#000000" vertex="1" parent="a33fc998-6909-4699-b236-76cd1d775efd">
                    <mxGeometry y='26' width='150' height='26' as='geometry' />
                </mxCell>
                <mxCell id="b8805fb0-9039-47bb-a7b4-0b2113c38c6f" value="TARP" style="text;strokeColor=none;fillColor=none;align=left;verticalAlign=top;spacingLeft=4;spacingRight=4;overflow=hidden;rotatable=0;points=[[0,0.5],[1,0.5]];portConstraint=eastwest;fontColor=#000000" vertex="1" parent="a33fc998-6909-4699-b236-76cd1d775efd">
                    <mxGeometry y='26' width='150' height='26' as='geometry' />
                </mxCell>
                <mxCell id="7e80ea38-eedf-4f08-9aa2-b0a23d86d730" value="MoWiTT" style="text;strokeColor=none;fillColor=none;align=left;verticalAlign=top;spacingLeft=4;spacingRight=4;overflow=hidden;rotatable=0;points=[[0,0.5],[1,0.5]];portConstraint=eastwest;fontColor=#000000" vertex="1" parent="a33fc998-6909-4699-b236-76cd1d775efd">
                    <mxGeometry y='26' width='150' height='26' as='geometry' />
                </mxCell>
                <mxCell id="6f559548-8ff7-4c33-b590-e3a6b09cff78" value="DOE2" style="text;strokeColor=none;fillColor=none;align=left;verticalAlign=top;spacingLeft=4;spacingRight=4;overflow=hidden;rotatable=0;points=[[0,0.5],[1,0.5]];portConstraint=eastwest;fontColor=#000000" vertex="1" parent="a33fc998-6909-4699-b236-76cd1d775efd">
                    <mxGeometry y='26' width='150' height='26' as='geometry' />
                </mxCell>
                <mxCell id="ecb6deef-b5c3-47bc-9201-46e43816e5ef" value="AdaptiveConvectionAlgorithm" style="text;strokeColor=none;fillColor=none;align=left;verticalAlign=top;spacingLeft=4;spacingRight=4;overflow=hidden;rotatable=0;points=[[0,0.5],[1,0.5]];portConstraint=eastwest;fontColor=#000000" vertex="1" parent="a33fc998-6909-4699-b236-76cd1d775efd">
                    <mxGeometry y='26' width='150' height='26' as='geometry' />
                </mxCell>
            </root>
        </mxGraphModel dx='-1266' dy='2416' grid='1' gridSize='10' guides='1' tooltips='1' connect='1' arrows='1' fold='1' page='1' pageScale='1' pageWidth='1169' pageHeight='827' math='0' shadow='0'>
    </diagram id='af4a872b-a1f0-4bc1-b211-2ba1853a3685'>
</mxfile host='Electron' modified='24/06/2021 15:05:18' agent='BHoM' type='device'>