<mxfile host='Electron' modified='24/06/2021 15:05:34' agent='BHoM' type='device'>
    <diagram id='e6fa7bef-ab47-4dee-8bb1-4e89a06f0c87'>
        <mxGraphModel dx='-1266' dy='2416' grid='1' gridSize='10' guides='1' tooltips='1' connect='1' arrows='1' fold='1' page='1' pageScale='1' pageWidth='1169' pageHeight='827' math='0' shadow='0'>
            <root>
                <mxCell id="764d0fa8-899e-4ea5-8841-bcdb64ceee09" />
                <mxCell id="a061bb0f-75b8-494f-80b0-b9e6b3cffc2e" parent="764d0fa8-899e-4ea5-8841-bcdb64ceee09" />
                <mxCell id="8ccf05a6-4edd-4f6b-96a7-4cde5bc83259" value="&lt;&lt;enumeration&gt;&gt;&#xD;&#xA;MaterialDB" style="swimlane;fontStyle=0;childLayout=stackLayout;horizontal=1;startSize=42;fillColor=none;horizontalStack=0;resizeParent=1;resizeParentMax=0;resizeLast=0;collapsible=1;marginBottom=0;fontSize=12;align=center;" vertex="1" collapsed="1" parent="a061bb0f-75b8-494f-80b0-b9e6b3cffc2e">
                    <mxGeometry x="0" y="0" width="200" height="42" as="geometry">
                        <mxRectangle x='0' y='0' width='230' height='192' as='alternateBounds' />
                    </mxGeometry>
                </mxCell>
                <mxCell id="beb4370d-ef99-40e7-adf9-e77fe97deff3" value="American" style="text;strokeColor=none;fillColor=none;align=left;verticalAlign=top;spacingLeft=4;spacingRight=4;overflow=hidden;rotatable=0;points=[[0,0.5],[1,0.5]];portConstraint=eastwest;fontColor=#000000" vertex="1" parent="8ccf05a6-4edd-4f6b-96a7-4cde5bc83259">
                    <mxGeometry y='26' width='150' height='26' as='geometry' />
                </mxCell>
                <mxCell id="fdd8ec4e-a90f-4e37-bb44-4d64f11a9769" value="British" style="text;strokeColor=none;fillColor=none;align=left;verticalAlign=top;spacingLeft=4;spacingRight=4;overflow=hidden;rotatable=0;points=[[0,0.5],[1,0.5]];portConstraint=eastwest;fontColor=#000000" vertex="1" parent="8ccf05a6-4edd-4f6b-96a7-4cde5bc83259">
                    <mxGeometry y='26' width='150' height='26' as='geometry' />
                </mxCell>
                <mxCell id="b56a8373-c6e6-4450-be3f-1c4cc5f24a1c" value="Eurocode" style="text;strokeColor=none;fillColor=none;align=left;verticalAlign=top;spacingLeft=4;spacingRight=4;overflow=hidden;rotatable=0;points=[[0,0.5],[1,0.5]];portConstraint=eastwest;fontColor=#000000" vertex="1" parent="8ccf05a6-4edd-4f6b-96a7-4cde5bc83259">
                    <mxGeometry y='26' width='150' height='26' as='geometry' />
                </mxCell>
            </root>
        </mxGraphModel dx='-1266' dy='2416' grid='1' gridSize='10' guides='1' tooltips='1' connect='1' arrows='1' fold='1' page='1' pageScale='1' pageWidth='1169' pageHeight='827' math='0' shadow='0'>
    </diagram id='e6fa7bef-ab47-4dee-8bb1-4e89a06f0c87'>
</mxfile host='Electron' modified='24/06/2021 15:05:34' agent='BHoM' type='device'>