<mxfile host='Electron' modified='24/06/2021 15:05:19' agent='BHoM' type='device'>
    <diagram id='b5544f4c-27e9-49bb-8900-86df1c0af0d7'>
        <mxGraphModel dx='-1266' dy='2416' grid='1' gridSize='10' guides='1' tooltips='1' connect='1' arrows='1' fold='1' page='1' pageScale='1' pageWidth='1169' pageHeight='827' math='0' shadow='0'>
            <root>
                <mxCell id="484a6082-c910-441a-8f50-fdd2677dc3df" />
                <mxCell id="ab829047-10ab-410a-9a88-4a5edfd44c7d" parent="484a6082-c910-441a-8f50-fdd2677dc3df" />
                <mxCell id="19cb4dfb-b370-4ce3-8691-57ca667999bd" value="&lt;&lt;enumeration&gt;&gt;&#xD;&#xA;SortOrder" style="swimlane;fontStyle=0;childLayout=stackLayout;horizontal=1;startSize=42;fillColor=none;horizontalStack=0;resizeParent=1;resizeParentMax=0;resizeLast=0;collapsible=1;marginBottom=0;fontSize=12;align=center;" vertex="1" collapsed="1" parent="ab829047-10ab-410a-9a88-4a5edfd44c7d">
                    <mxGeometry x="0" y="0" width="200" height="42" as="geometry">
                        <mxRectangle x='0' y='0' width='230' height='192' as='alternateBounds' />
                    </mxGeometry>
                </mxCell>
                <mxCell id="c630422e-468e-43bb-8e2a-11224351c053" value="Default" style="text;strokeColor=none;fillColor=none;align=left;verticalAlign=top;spacingLeft=4;spacingRight=4;overflow=hidden;rotatable=0;points=[[0,0.5],[1,0.5]];portConstraint=eastwest;fontColor=#000000" vertex="1" parent="19cb4dfb-b370-4ce3-8691-57ca667999bd">
                    <mxGeometry y='26' width='150' height='26' as='geometry' />
                </mxCell>
                <mxCell id="65933c80-ffb9-4f43-bf3c-7e41df94b6ca" value="ByName" style="text;strokeColor=none;fillColor=none;align=left;verticalAlign=top;spacingLeft=4;spacingRight=4;overflow=hidden;rotatable=0;points=[[0,0.5],[1,0.5]];portConstraint=eastwest;fontColor=#000000" vertex="1" parent="19cb4dfb-b370-4ce3-8691-57ca667999bd">
                    <mxGeometry y='26' width='150' height='26' as='geometry' />
                </mxCell>
                <mxCell id="775c5892-8519-469b-a5c9-0bdba5c3184b" value="BySize" style="text;strokeColor=none;fillColor=none;align=left;verticalAlign=top;spacingLeft=4;spacingRight=4;overflow=hidden;rotatable=0;points=[[0,0.5],[1,0.5]];portConstraint=eastwest;fontColor=#000000" vertex="1" parent="19cb4dfb-b370-4ce3-8691-57ca667999bd">
                    <mxGeometry y='26' width='150' height='26' as='geometry' />
                </mxCell>
                <mxCell id="2b05d7cf-d392-4635-801e-6dee6da48735" value="ByCreationTime" style="text;strokeColor=none;fillColor=none;align=left;verticalAlign=top;spacingLeft=4;spacingRight=4;overflow=hidden;rotatable=0;points=[[0,0.5],[1,0.5]];portConstraint=eastwest;fontColor=#000000" vertex="1" parent="19cb4dfb-b370-4ce3-8691-57ca667999bd">
                    <mxGeometry y='26' width='150' height='26' as='geometry' />
                </mxCell>
                <mxCell id="fa876041-a4b9-4ee7-be38-153f31a0be79" value="ByLastModifiedTime" style="text;strokeColor=none;fillColor=none;align=left;verticalAlign=top;spacingLeft=4;spacingRight=4;overflow=hidden;rotatable=0;points=[[0,0.5],[1,0.5]];portConstraint=eastwest;fontColor=#000000" vertex="1" parent="19cb4dfb-b370-4ce3-8691-57ca667999bd">
                    <mxGeometry y='26' width='150' height='26' as='geometry' />
                </mxCell>
            </root>
        </mxGraphModel dx='-1266' dy='2416' grid='1' gridSize='10' guides='1' tooltips='1' connect='1' arrows='1' fold='1' page='1' pageScale='1' pageWidth='1169' pageHeight='827' math='0' shadow='0'>
    </diagram id='b5544f4c-27e9-49bb-8900-86df1c0af0d7'>
</mxfile host='Electron' modified='24/06/2021 15:05:19' agent='BHoM' type='device'>