<mxfile host='Electron' modified='24/06/2021 15:05:19' agent='BHoM' type='device'>
    <diagram id='921feb34-6a70-456b-8891-901da9717e80'>
        <mxGraphModel dx='-1266' dy='2416' grid='1' gridSize='10' guides='1' tooltips='1' connect='1' arrows='1' fold='1' page='1' pageScale='1' pageWidth='1169' pageHeight='827' math='0' shadow='0'>
            <root>
                <mxCell id="9f09c464-0b2c-405a-80af-38b0b08459e7" />
                <mxCell id="6965c15b-d2e5-498c-927c-659999170d29" parent="9f09c464-0b2c-405a-80af-38b0b08459e7" />
                <mxCell id="2f29f592-dcfa-4b0c-b26d-ca57335f2756" value="&lt;&lt;interface&gt;&gt;&#xD;&#xA;IFileRequest" style="swimlane;fontStyle=0;childLayout=stackLayout;horizontal=1;startSize=42;fillColor=none;horizontalStack=0;resizeParent=1;resizeParentMax=0;resizeLast=0;collapsible=1;marginBottom=0;fontSize=12;align=center;" vertex="1" collapsed="1" parent="6965c15b-d2e5-498c-927c-659999170d29">
                    <mxGeometry x="0" y="0" width="200" height="42" as="geometry">
                        <mxRectangle x='0' y='0' width='230' height='192' as='alternateBounds' />
                    </mxGeometry>
                </mxCell>
                <mxCell id="77c7bf34-4942-405d-9403-5b74b084e9f4" value="MaxFiles : Int32" style="text;strokeColor=none;fillColor=none;align=left;verticalAlign=top;spacingLeft=4;spacingRight=4;overflow=hidden;rotatable=0;points=[[0,0.5],[1,0.5]];portConstraint=eastwest;fontColor=#000000" vertex="1" parent="2f29f592-dcfa-4b0c-b26d-ca57335f2756">
                    <mxGeometry y='26' width='150' height='26' as='geometry' />
                </mxCell>
                <mxCell id="a7e29070-183a-49e1-b1e7-c793a2385b0b" value="IncludeFileContents : Boolean" style="text;strokeColor=none;fillColor=none;align=left;verticalAlign=top;spacingLeft=4;spacingRight=4;overflow=hidden;rotatable=0;points=[[0,0.5],[1,0.5]];portConstraint=eastwest;fontColor=#000000" vertex="1" parent="2f29f592-dcfa-4b0c-b26d-ca57335f2756">
                    <mxGeometry y='26' width='150' height='26' as='geometry' />
                </mxCell>
                <mxCell id="a5aefd0d-14bc-423b-bab4-99acc78c692d" value="Location : String" style="text;strokeColor=none;fillColor=none;align=left;verticalAlign=top;spacingLeft=4;spacingRight=4;overflow=hidden;rotatable=0;points=[[0,0.5],[1,0.5]];portConstraint=eastwest;fontColor=#707070" vertex="1" parent="2f29f592-dcfa-4b0c-b26d-ca57335f2756">
                    <mxGeometry y='26' width='150' height='26' as='geometry' />
                </mxCell>
                <mxCell id="90ebf9c1-7449-4367-a8da-0472e8588da6" value="SearchSubdirectories : Boolean" style="text;strokeColor=none;fillColor=none;align=left;verticalAlign=top;spacingLeft=4;spacingRight=4;overflow=hidden;rotatable=0;points=[[0,0.5],[1,0.5]];portConstraint=eastwest;fontColor=#707070" vertex="1" parent="2f29f592-dcfa-4b0c-b26d-ca57335f2756">
                    <mxGeometry y='26' width='150' height='26' as='geometry' />
                </mxCell>
                <mxCell id="4506876b-ca9f-493e-9e51-4307a0576d13" value="Exclusions : List&lt;Object&gt;" style="text;strokeColor=none;fillColor=none;align=left;verticalAlign=top;spacingLeft=4;spacingRight=4;overflow=hidden;rotatable=0;points=[[0,0.5],[1,0.5]];portConstraint=eastwest;fontColor=#707070" vertex="1" parent="2f29f592-dcfa-4b0c-b26d-ca57335f2756">
                    <mxGeometry y='26' width='150' height='26' as='geometry' />
                </mxCell>
                <mxCell id="0e8fc08c-7b4c-44d4-b345-17322a36d185" value="SortOrder : SortOrder" style="text;strokeColor=none;fillColor=none;align=left;verticalAlign=top;spacingLeft=4;spacingRight=4;overflow=hidden;rotatable=0;points=[[0,0.5],[1,0.5]];portConstraint=eastwest;fontColor=#707070" vertex="1" parent="2f29f592-dcfa-4b0c-b26d-ca57335f2756">
                    <mxGeometry y='26' width='150' height='26' as='geometry' />
                </mxCell>
            </root>
        </mxGraphModel dx='-1266' dy='2416' grid='1' gridSize='10' guides='1' tooltips='1' connect='1' arrows='1' fold='1' page='1' pageScale='1' pageWidth='1169' pageHeight='827' math='0' shadow='0'>
    </diagram id='921feb34-6a70-456b-8891-901da9717e80'>
</mxfile host='Electron' modified='24/06/2021 15:05:19' agent='BHoM' type='device'>