<mxfile host='Electron' modified='24/06/2021 15:05:35' agent='BHoM' type='device'>
    <diagram id='0c5461b4-0135-43f8-8993-0a8af8566ac9'>
        <mxGraphModel dx='-1266' dy='2416' grid='1' gridSize='10' guides='1' tooltips='1' connect='1' arrows='1' fold='1' page='1' pageScale='1' pageWidth='1169' pageHeight='827' math='0' shadow='0'>
            <root>
                <mxCell id="f6b452cb-de22-41b6-9f03-5281204a2e79" />
                <mxCell id="03151152-6e6a-41e6-9d96-d09f1173dea8" parent="f6b452cb-de22-41b6-9f03-5281204a2e79" />
                <mxCell id="93abb537-c8fa-457d-b732-3622c6b03fdb" value="UniformLoadSet" style="swimlane;fontStyle=0;childLayout=stackLayout;horizontal=1;startSize=26;fillColor=none;horizontalStack=0;resizeParent=1;resizeParentMax=0;resizeLast=0;collapsible=1;marginBottom=0;fontSize=12;align=left;spacingLeft=15;" vertex="1" collapsed="1" parent="03151152-6e6a-41e6-9d96-d09f1173dea8">
                    <mxGeometry x="0" y="0" width="150" height="26" as="geometry">
                        <mxRectangle x='0' y='0' width='230' height='176' as='alternateBounds' />
                    </mxGeometry>
                </mxCell>
                <mxCell id="22b4664f-3b8b-4a1e-bf86-0da8fc7f1468" value="Name : String" style="text;strokeColor=none;fillColor=none;align=left;verticalAlign=top;spacingLeft=4;spacingRight=4;overflow=hidden;rotatable=0;points=[[0,0.5],[1,0.5]];portConstraint=eastwest;fontColor=#000000" vertex="1" parent="93abb537-c8fa-457d-b732-3622c6b03fdb">
                    <mxGeometry y='26' width='150' height='26' as='geometry' />
                </mxCell>
                <mxCell id="24d6579e-f89a-4645-ac39-31c4e07590a6" value="Loads : List&lt;UniformLoadSetRecord&gt;" style="text;strokeColor=none;fillColor=none;align=left;verticalAlign=top;spacingLeft=4;spacingRight=4;overflow=hidden;rotatable=0;points=[[0,0.5],[1,0.5]];portConstraint=eastwest;fontColor=#000000" vertex="1" parent="93abb537-c8fa-457d-b732-3622c6b03fdb">
                    <mxGeometry y='26' width='150' height='26' as='geometry' />
                </mxCell>
                <mxCell id="2113064a-f446-4b83-b52d-1f89c97ecf42" value="BHoM_Guid : Guid" style="text;strokeColor=none;fillColor=none;align=left;verticalAlign=top;spacingLeft=4;spacingRight=4;overflow=hidden;rotatable=0;points=[[0,0.5],[1,0.5]];portConstraint=eastwest;fontColor=#707070" vertex="1" parent="93abb537-c8fa-457d-b732-3622c6b03fdb">
                    <mxGeometry y='26' width='150' height='26' as='geometry' />
                </mxCell>
                <mxCell id="c24d7b0c-06b4-431a-887a-ba1078b03861" value="Fragments : FragmentSet" style="text;strokeColor=none;fillColor=none;align=left;verticalAlign=top;spacingLeft=4;spacingRight=4;overflow=hidden;rotatable=0;points=[[0,0.5],[1,0.5]];portConstraint=eastwest;fontColor=#707070" vertex="1" parent="93abb537-c8fa-457d-b732-3622c6b03fdb">
                    <mxGeometry y='26' width='150' height='26' as='geometry' />
                </mxCell>
                <mxCell id="1e518df7-db7d-4ff2-8be8-47eba8094b35" value="Tags : HashSet&lt;String&gt;" style="text;strokeColor=none;fillColor=none;align=left;verticalAlign=top;spacingLeft=4;spacingRight=4;overflow=hidden;rotatable=0;points=[[0,0.5],[1,0.5]];portConstraint=eastwest;fontColor=#707070" vertex="1" parent="93abb537-c8fa-457d-b732-3622c6b03fdb">
                    <mxGeometry y='26' width='150' height='26' as='geometry' />
                </mxCell>
                <mxCell id="57c6209d-64c0-426c-a201-a344a9a20fe7" value="CustomData : Dictionary&lt;String,Object&gt;" style="text;strokeColor=none;fillColor=none;align=left;verticalAlign=top;spacingLeft=4;spacingRight=4;overflow=hidden;rotatable=0;points=[[0,0.5],[1,0.5]];portConstraint=eastwest;fontColor=#707070" vertex="1" parent="93abb537-c8fa-457d-b732-3622c6b03fdb">
                    <mxGeometry y='26' width='150' height='26' as='geometry' />
                </mxCell>
            </root>
        </mxGraphModel dx='-1266' dy='2416' grid='1' gridSize='10' guides='1' tooltips='1' connect='1' arrows='1' fold='1' page='1' pageScale='1' pageWidth='1169' pageHeight='827' math='0' shadow='0'>
    </diagram id='0c5461b4-0135-43f8-8993-0a8af8566ac9'>
</mxfile host='Electron' modified='24/06/2021 15:05:35' agent='BHoM' type='device'>